dgm_fit/__init__.py
dgm_fit/fit_result.py
dgm_fit/iminuit_minimizer.py
dgm_fit/minimizable.py
dgm_fit/minimizer_base.py
dgm_fit-0.2.dist-info/licenses/LICENSE
dgm_fit-0.2.dist-info/METADATA
dgm_fit-0.2.dist-info/WHEEL
dgm_fit-0.2.dist-info/top_level.txt
dgm_fit-0.2.dist-info/RECORD
