Metadata-Version: 2.4
Name: dgm-fit
Version: 0.2
Summary: The package implements the fitter interface for the dag-modelling framework
Author-email: DAGModelling Team <dagflow@jinr.ru>
Maintainer-email: DAGModelling Team <dagflow@jinr.ru>
License-Expression: MIT
Project-URL: Bug Tracker, https://github.com/dagflow-team/dgm-fit/issues
Project-URL: DAGModelling Team, https://github.com/dagflow-team
Project-URL: documentation, https://github.com/dagflow-team/dgm-fit/wiki
Project-URL: homepage, https://github.com/dagflow-team/dgm-fit
Project-URL: repository, https://github.com/dagflow-team/dgm-fit
Classifier: Programming Language :: Python :: 3 :: Only
Classifier: Programming Language :: Python :: 3.11
Classifier: Programming Language :: Python :: 3.12
Classifier: Programming Language :: Python :: 3.13
Requires-Python: >=3.11
License-File: LICENSE
Requires-Dist: dag-modelling
Requires-Dist: iminuit
Requires-Dist: numba
Requires-Dist: scipy
Provides-Extra: test
Requires-Dist: coverage; extra == "test"
Requires-Dist: pytest; extra == "test"
Requires-Dist: pytest-cov; extra == "test"
Dynamic: license-file
